glowkit/__init__.py
glowkit/animation.py
glowkit/app.py
glowkit/core.py
glowkit/crash.py
glowkit/dev.py
glowkit/splash.py
glowkit/state.py
glowkit/styles.py
glowkit/themes.py
glowkit/toast.py
glowkit/widgets.py
glowkit-0.3.1.dist-info/licenses/LICENSE
glowkit-0.3.1.dist-info/METADATA
glowkit-0.3.1.dist-info/WHEEL
glowkit-0.3.1.dist-info/top_level.txt
glowkit-0.3.1.dist-info/RECORD
