Metadata-Version: 2.4
Name: glowkit
Version: 0.3.1
Summary: Glowkit - a declarative Python GUI toolkit
Author: SkitDev
License: MIT
Project-URL: Repository, https://github.com/SkitDev/GlowKit
Keywords: gui,declarative,tkinter,desktop
Classifier: Programming Language :: Python :: 3
Classifier: License :: OSI Approved :: MIT License
Classifier: Operating System :: OS Independent
Classifier: Topic :: Software Development :: User Interfaces
Requires-Python: >=3.9
License-File: LICENSE
Dynamic: license-file
